tfhubartifact/TensorFlowHubModelArtifact.py
tfhubartifact/__init__.py
tfhubartifact-0.0.6.dist-info/METADATA
tfhubartifact-0.0.6.dist-info/WHEEL
tfhubartifact-0.0.6.dist-info/top_level.txt
tfhubartifact-0.0.6.dist-info/RECORD
