Metadata-Version: 2.1
Name: tfhubartifact
Version: 0.0.6
Summary: BentoML artifact framework for TensorFlow Hub models
Home-page: https://github.com/markmo/tfhubartifact
Author: Mark Moloney
Author-email: m4rkmo@gmail.com
License: UNKNOWN
Platform: UNKNOWN
Classifier: Programming Language :: Python :: 3
Classifier: License :: OSI Approved :: MIT License
Classifier: Operating System :: OS Independent
Requires-Python: >=3.6
